AUTHORS.rst
CONTRIBUTING.rst
HISTORY.rst
LICENSE
MANIFEST.in
README.rst
setup.cfg
setup.py
docs/Makefile
docs/authors.rst
docs/conf.py
docs/contributing.rst
docs/history.rst
docs/index.rst
docs/installation.rst
docs/make.bat
docs/readme.rst
docs/usage.rst
gbrs/__init__.py
gbrs/commands.py
gbrs/emase_utils.py
gbrs/g2g_utils.py
gbrs/gbrs_utils.py
gbrs.egg-info/PKG-INFO
gbrs.egg-info/SOURCES.txt
gbrs.egg-info/dependency_links.txt
gbrs.egg-info/not-zip-safe
gbrs.egg-info/requires.txt
gbrs.egg-info/top_level.txt
scripts/convert-kallisto-result-for-gbrs
scripts/convert-salmon-result-for-gbrs
scripts/gbrs
tests/__init__.py
tests/test_gbrs.py