Metadata-Version: 1.1
Name: gbrs
Version: 0.1.5
Summary: A suite of tools for Reconstructing Genomes and Quantifying Allele Specific Expression from RNA-Seq data
Home-page: https://github.com/churchill-lab/gbrs
Author: Kwangbom "KB" Choi, Ph.D.
Author-email: kb.choi@jax.org
License: GPLv3
Keywords: gbrs
Platform: UNKNOWN
Classifier: Development Status :: 4 - Beta
Classifier: Intended Audience :: Developers
Classifier: License :: OSI Approved :: GNU General Public License v3 (GPLv3)
Classifier: Natural Language :: English
Classifier: Programming Language :: Python :: 2.7
